jumpstart_projects
