Metadata-Version: 2.1
Name: jumpstart-projects
Version: 0.1.1
Summary: Project jumpstart utilities
Home-page: UNKNOWN
Author: Aradhya
Author-email: aradhyatripathi51@gmail.com
License: UNKNOWN
Platform: UNKNOWN
Requires-Python: >=3.8,<4.0
